{
    "header": {
        "site": "reference",
        "comment": ""
    },
    "primary": {
        "modules": [
            "ahci",
            "xhci_pci",
            "xhci_hcd",
            "sd_mod",
            "scsi_mod",
            "igb",
            "ipv6",
            "btrfs",
            "usbhid",
            "hid_generic",
            "hid",
            "usbserial",
            "dm_mod",
            "dm_crypt",
            "aes",
            "tpm_tis_core",
            "tpm_tis",
            "tpm_crb",
            "tpm",
            "uas",
            "vfat",
            "fat",
            "nls_utf8",
            "nls_cp437",
            "wireguard",
            "nvme"
        ],
        "filesystem": {
            "devices": [
                {
                    "label": "BOOT",
                    "id": "/dev/sda1",
                    "mountpoint": "/boot",
                    "filesystem": "ext4"
                },
                {
                    "label": "CONFIG",
                    "id": "/dev/sda2",
                    "mountpoint": "/var/config",
                    "filesystem": "ext4"
                },
                {
                    "label": "DATA",
                    "id": "/dev/sda3",
                    "mountpoint": "/var/lib/docker",
                    "filesystem": "ext4"
                }
            ]
        }
    }
}